cjdb/__init__.py
ChefsJsonDB-1.0.0.dist-info/LICENCE.txt
ChefsJsonDB-1.0.0.dist-info/METADATA
ChefsJsonDB-1.0.0.dist-info/WHEEL
ChefsJsonDB-1.0.0.dist-info/top_level.txt
ChefsJsonDB-1.0.0.dist-info/RECORD
