Metadata-Version: 2.1
Name: ChefsJsonDB
Version: 1.0.0
Summary: database for python users with easy to use and modify Json files
Author: Noam Avned
License: MIT
Classifier: Development Status :: 5 - Production/Stable
Classifier: Intended Audience :: Education
Classifier: Operating System :: Microsoft :: Windows :: Windows 10
Classifier: License :: OSI Approved :: MIT License
Classifier: Programming Language :: Python :: 3
License-File: LICENCE.txt
